Metadata-Version: 2.4
Name: pythonbpf
Version: 0.1.6
Summary: Reduced Python frontend for eBPF
Author-email: r41k0u <pragyanshchaturvedi18@gmail.com>, varun-r-mallya <varunrmallya@gmail.com>
License: Apache-2.0
Classifier: Development Status :: 3 - Alpha
Classifier: Intended Audience :: Developers
Classifier: Operating System :: POSIX :: Linux
Classifier: Programming Language :: Python :: 3
Classifier: Programming Language :: Python :: 3.8
Classifier: Programming Language :: Python :: 3.9
Classifier: Programming Language :: Python :: 3.10
Classifier: Programming Language :: Python :: 3.11
Classifier: Programming Language :: Python :: 3.12
Classifier: Programming Language :: Python
Classifier: Topic :: Software Development :: Libraries :: Python Modules
Classifier: Topic :: System :: Operating System Kernels :: Linux
Requires-Python: >=3.8
License-File: LICENSE
Requires-Dist: llvmlite
Requires-Dist: astpretty
Requires-Dist: pylibbpf
Dynamic: license-file
